odoo/addons/l10n_es_intrastat_report/README.rst
odoo/addons/l10n_es_intrastat_report/__init__.py
odoo/addons/l10n_es_intrastat_report/__manifest__.py
odoo/addons/l10n_es_intrastat_report/hooks.py
odoo/addons/l10n_es_intrastat_report/data/Estruc_NC2023.xlsx
odoo/addons/l10n_es_intrastat_report/data/NC_20.xls
odoo/addons/l10n_es_intrastat_report/data/intrastat_transaction.xml
odoo/addons/l10n_es_intrastat_report/i18n/ca.po
odoo/addons/l10n_es_intrastat_report/i18n/es.po
odoo/addons/l10n_es_intrastat_report/i18n/l10n_es_intrastat_report.pot
odoo/addons/l10n_es_intrastat_report/models/__init__.py
odoo/addons/l10n_es_intrastat_report/models/l10n_es_intrastat_product_declaration.py
odoo/addons/l10n_es_intrastat_report/models/stock_location.py
odoo/addons/l10n_es_intrastat_report/models/template_es_common_mainland.py
odoo/addons/l10n_es_intrastat_report/readme/CONFIGURE.md
odoo/addons/l10n_es_intrastat_report/readme/CONTRIBUTORS.md
odoo/addons/l10n_es_intrastat_report/readme/DESCRIPTION.md
odoo/addons/l10n_es_intrastat_report/readme/INSTALL.md
odoo/addons/l10n_es_intrastat_report/readme/ROADMAP.md
odoo/addons/l10n_es_intrastat_report/readme/USAGE.md
odoo/addons/l10n_es_intrastat_report/report/__init__.py
odoo/addons/l10n_es_intrastat_report/report/intrastat_product_report_xls.py
odoo/addons/l10n_es_intrastat_report/security/ir.model.access.csv
odoo/addons/l10n_es_intrastat_report/static/description/icon.png
odoo/addons/l10n_es_intrastat_report/static/description/index.html
odoo/addons/l10n_es_intrastat_report/tests/__init__.py
odoo/addons/l10n_es_intrastat_report/tests/test_l10n_es_intrastat_report.py
odoo/addons/l10n_es_intrastat_report/views/l10n_es_intrastat_product.xml
odoo/addons/l10n_es_intrastat_report/wizards/__init__.py
odoo/addons/l10n_es_intrastat_report/wizards/l10n_es_intrastat_code_import.py
odoo/addons/l10n_es_intrastat_report/wizards/l10n_es_intrastat_code_import.xml
odoo_addon_l10n_es_intrastat_report-18.0.1.1.0.dist-info/METADATA
odoo_addon_l10n_es_intrastat_report-18.0.1.1.0.dist-info/WHEEL
odoo_addon_l10n_es_intrastat_report-18.0.1.1.0.dist-info/top_level.txt
odoo_addon_l10n_es_intrastat_report-18.0.1.1.0.dist-info/RECORD
